{
	"animations": [
		{
			"loop": false,
			"offset": [
				7,
				0
			],
			"fps": 24,
			"anim": "firstDeath",
			"indices": [],
			"prefix": "BF Dies pixel"
		},
		{
			"loop": false,
			"offset": [
				0,
				0
			],
			"anim": "deathLoop",
			"fps": 24,
			"prefix": "Retry Loop",
			"indices": []
		},
		{
			"loop": false,
			"offset": [
				0,
				0
			],
			"anim": "deathConfirm",
			"fps": 24,
			"prefix": "RETRY CONFIRM",
			"indices": []
		}
	],
	"noAntialiasing": true,
	"image": "characters/bfPixelsDEAD",
	"positionOffset": [
		0,
		0
	],
	"healthIcon": "icon-bf-pixel",
	"flipX": true,
	"healthColors": [
		123,
		214,
		246
	],
	"camOffset": [
		-450,
		-200
	],
	"scale": 6
}